<?xml version="1.0" encoding="utf-8"?>
<odoo>
    <data>
        <!--Monthly Revenue menu-->
        <!-- <menuitem id="crm_monthly_revenue_report_menu" name="Monthly Revenue"
            parent="sales_team.menu_sale_report" action="crm_monthly_revenue_report_action" sequence="10"/>
	    	 -->
	    <!--Monthly Revenue Split menu-->
        <menuitem id="crm_monthly_revenue_split_report_menu" name="Monthly Revenue Split"
            parent="sale.menu_sale_report" action="crm_monthly_revenue_split_report_action" sequence="10"/>
            
    	<!-- Link Tracker Menu -->
     	<record id="utm.menu_link_tracker_root" model="ir.ui.menu">
    		<field name="groups_id" eval="[(6,0,[ref('magnus_crm.group_link_tracker')])]"/>
		</record>


        <!--<menuitem-->
            <!--id="sales_team.menu_sales"-->
            <!--name="Sales"-->
            <!--parent="sales_team.menu_base_partner"-->
            <!--sequence="5"/>-->
        <!---->
        <!--<menuitem id="menu_product" name="Product Variants" parent="sales_team.menu_base_partner" sequence="9" groups="product.group_product_variant"/>-->
			<!---->

        <!--<menuitem
            id="menu_crm_config_lead"
            name="Leads &amp; Opportunities"
            parent="sales_team.menu_sale_config"
            sequence="5"
            groups="sales_team.group_sale_manager"/>

        <menuitem
            id="menu_crm_config_opportunity"
            name="Opportunities"
            parent="sales_team.menu_sale_config"
            sequence="1"
            groups="sales_team.group_sale_manager"/>

        <menuitem name="Sales Teams"
            id="sales_team_config"
            parent="sales_team.menu_sale_config"
            action="sales_team_config_action"/>

        <menuitem id="sale.prod_config_main" name="Products" parent="sales_team.menu_sale_config" sequence="2"/>

        <menuitem id="menu_product_pricelist_main" name="Pricelists" parent="sales_team.menu_sale_config" groups="product.group_sale_pricelist" sequence="3"/>-->

        <!--<record model="ir.ui.menu" id="sales_team.menu_sale_config">-->
            <!--<field name="name">Configuration</field>-->
            <!--<field eval="[(6,0,[ref('base.group_system')])]" name="groups_id"/>-->
        <!--</record>-->

        <!--<menuitem id="sales_team.menu_sales" name="Sales" parent="sales_team.menu_base_partner" groups="magnus_crm.group_sale_regular_user"-->
                  <!--sequence="5"/>-->
        <!---->
        <!--<menuitem-->
            <!--id="sales_team.menu_sales"-->
            <!--name="Sales"-->
            <!--parent="sales_team.menu_base_partner"-->
            <!--sequence="5"/>-->

        <menuitem name="Sales"
                id="sale.sale_menu_root"
                groups="magnus_crm.group_sale_regular_user" sequence="6"/>

        <menuitem action="sale.action_orders"
            id="sale.menu_sale_order" parent="sales_team.menu_sales"
            sequence="12" groups="magnus_crm.group_sale_regular_user"/>

        <menuitem id="sales_team.menu_sale_report" name="Reports" parent="sales_team.menu_base_partner" sequence="99" groups="sales_team.group_sale_manager,magnus_crm.group_sale_regular_user"/>

         <menuitem
            id="crm.crm_activity_report_menu"
            name="Activities"
            groups="sales_team.group_sale_manager,magnus_crm.group_sale_regular_user"
            parent="sales_team.menu_sale_report"
            action="crm.crm_activity_report_action"
            sequence="7"/>

    </data>
</odoo>